ado.py
ado_py-0.1.1.dist-info/entry_points.txt
ado_py-0.1.1.dist-info/LICENSE
ado_py-0.1.1.dist-info/WHEEL
ado_py-0.1.1.dist-info/METADATA
ado_py-0.1.1.dist-info/RECORD
