Metadata-Version: 2.1
Name: ado-py
Version: 0.1.1
Summary: Do stuff with python. Quickly access functions defied in do.py from the command-line.
Home-page: https://github.com/aahnik/ado-py
License: MIT
Keywords: python,cli,task runner
Author: aahnik
Author-email: daw@aahnik.dev
Requires-Python: >=3.6,<4.0
Classifier: Development Status :: 4 - Beta
Classifier: Intended Audience :: Education
Classifier: Intended Audience :: Information Technology
Classifier: License :: OSI Approved :: MIT License
Classifier: Natural Language :: English
Classifier: Operating System :: OS Independent
Classifier: Programming Language :: Python
Classifier: Programming Language :: Python :: 3
Classifier: Programming Language :: Python :: 3.6
Classifier: Programming Language :: Python :: 3.7
Classifier: Programming Language :: Python :: 3.8
Classifier: Programming Language :: Python :: 3.9
Project-URL: Repository, https://github.com/aahnik/ado-py
